fms_acceleration_ilab/__init__.py
fms_acceleration_ilab/flash_attn.py
fms_acceleration_ilab/framework_plugin_padding_free.py
fms_acceleration_ilab/ilab_utils.py
fms_acceleration_ilab-0.1.0.dist-info/METADATA
fms_acceleration_ilab-0.1.0.dist-info/WHEEL
fms_acceleration_ilab-0.1.0.dist-info/RECORD
