Metadata-Version: 2.3
Name: fms-acceleration-ilab
Version: 0.1.0
Summary: FMS Acceleration Plugin for Functionalities Used in Instruct Lab Training
Author-email: Fabian Lim <flim@sg.ibm.com>, Aaron Chew <aaron.chew1@ibm.com>
License: Apache-2.0
Keywords: acceleration,fms-hf-tuning,padding-free
Classifier: Development Status :: 4 - Beta
Classifier: License :: OSI Approved :: Apache Software License
Classifier: Programming Language :: Python :: 3
Classifier: Programming Language :: Python :: 3.9
Classifier: Programming Language :: Python :: 3.10
Classifier: Programming Language :: Python :: 3.11
Requires-Python: ~=3.9
